{
  "window": {
    "size": [
      1080,
      930
    ],
    "pos": [
      1920,
      -570
    ]
  },
  "table": {
    "column_widths": {
      "0": 40,
      "1": 0,
      "2": 82,
      "3": 30,
      "4": 284,
      "5": 300,
      "6": 168,
      "7": 65,
      "8": 60
    },
    "row_heights": {
      "0": 51,
      "1": 163,
      "2": 115,
      "3": 131,
      "4": 115,
      "5": 131,
      "6": 51,
      "7": 83,
      "8": 83,
      "9": 83,
      "10": 99,
      "11": 99,
      "12": 83,
      "13": 131,
      "14": 115,
      "15": 99,
      "16": 147,
      "17": 115,
      "18": 99,
      "19": 67,
      "20": 51,
      "21": 115,
      "22": 131,
      "23": 99,
      "24": 115,
      "25": 99,
      "26": 115,
      "27": 99,
      "28": 51,
      "29": 51,
      "30": 51,
      "31": 67,
      "32": 51,
      "33": 99,
      "34": 99,
      "35": 51,
      "36": 99,
      "37": 115,
      "38": 243,
      "39": 131,
      "40": 51,
      "41": 211,
      "42": 115,
      "43": 115,
      "44": 195,
      "45": 179,
      "46": 35,
      "47": 115,
      "48": 115,
      "49": 115,
      "50": 83,
      "51": 51,
      "52": 51,
      "53": 51,
      "54": 99,
      "55": 99,
      "56": 35,
      "57": 35,
      "58": 99,
      "59": 131,
      "60": 115,
      "61": 147,
      "62": 163,
      "63": 99,
      "64": 195,
      "65": 195,
      "66": 67,
      "67": 131,
      "68": 115,
      "69": 115,
      "70": 131,
      "71": 131,
      "72": 115,
      "73": 131,
      "74": 131,
      "75": 51
    }
  },
  "sheets": {
    "hidden_indices": [
      5,
      6,
      7,
      8,
      9,
      10,
      11
    ]
  },
  "tabs": {
    "hidden_keys": [
      "gs:График дежурств",
      "gs:Лист42",
      "gs:Лист49",
      "gs:МУЛЬТИГО",
      "gs:Пин коды",
      "gs:Реестр отклонений",
      "gs:Справочник",
      "gs:Телефоны ТС",
      "gs:Чек-Лист",
      "local:localdata"
    ],
    "active_key": "local:logistx"
  },
  "layout_mode": {
    "mode": "vertical",
    "monitor": "second"
  },
  "highlight": {
    "duration_minutes": 114,
    "enabled_types": [
      "manual",
      "expired_unloads",
      "future_load"
    ],
    "future_load_threshold_hours": 3,
    "expired_unload_grace_minutes": 0
  },
  "log": {
    "audience": "admin"
  }
}